demuxalot/BDRhapsody_specific.py
demuxalot/__init__.py
demuxalot/cellranger_specific.py
demuxalot/demux.py
demuxalot/genotypes.py
demuxalot/snp_counter.py
demuxalot/snp_detection.py
demuxalot/utils.py
demuxalot-0.4.3.dist-info/METADATA
demuxalot-0.4.3.dist-info/WHEEL
demuxalot-0.4.3.dist-info/licenses/LICENSE
demuxalot-0.4.3.dist-info/RECORD
