Metadata-Version: 2.4
Name: demuxalot
Version: 0.4.3
Summary: Scalable and reliable demulitplexing for single-cell RNA sequencing.
Project-URL: Homepage, https://github.com/arogozhnikov/demuxalot
Author: Alex Rogozhnikov, System1 Biosciences
License: MIT
License-File: LICENSE
Keywords: bayesian modelling,demultiplexing,genotype learning,single cell RNA sequencing
Classifier: License :: OSI Approved :: MIT License
Classifier: Programming Language :: Python :: 3
Requires-Python: >=3.8
Requires-Dist: joblib
Requires-Dist: numpy
Requires-Dist: pandas
Requires-Dist: pyarrow
Requires-Dist: pysam
Requires-Dist: scipy
